{
  "mcpServers": {
    "tavily-mcp": {
      "command": "tavily-mcp",
      "env": {
        "TAVILY_API_KEY": "${env:TAVILY_API_KEY}"
      }
    },
    "fetch-mcp": {
      "command": "mcp-server-fetch",
      "args": ["--ignore-robots-txt"],
      "env": {
        "SSL_CERT_FILE": "/etc/ssl/certs/ca-certificates.crt"
      }
    },
    "playwright": {
      "command": "playwright-mcp",
      "args": ["--headless"]
    },
    "brave-search": {
      "command": "mcp-server-brave-search",
      "env": {
        "BRAVE_API_KEY": "${env:BRAVE_API_KEY}"
      }
    }
  }
}
